<?xml version="1.0" encoding="UTF-8"?>
<timetable xmlns:xsi="http://www.w3.org/2001/XMLSchema-instance"
    xsi:noNamespaceSchemaLocation="schedule.xsd">
    <days>
        <dayoftheweek day="Monday">
            <class>
                <day>Monday</day>
                <coursecode>COMP4711</coursecode>
                <classtype>Lec</classtype>
                <instructor>Jim jam</instructor>
                <building>SW1</building>
                <room>1025</room>
                <starttime>8:30</starttime>
                <endtime>11:30</endtime>
            </class>
        </dayoftheweek>
    </days>

    <courses>
        <course coursecode="COMP4711">
            <class>
                <day>Tuesday</day>
                <coursecode>COMP4711</coursecode>
                <classtype>Lab</classtype>
                <instructor>Jim jam</instructor>
                <building>SE12</building>
                <room>310</room>
                <starttime>10:30</starttime>
                <endtime>11:30</endtime>
            </class>
        </course>
    </courses>

    <periods>
        <timeslot time="8:30">
            <class>
                <day>Wednesday</day>
                <coursecode>COMP4735</coursecode>
                <classtype>Lab</classtype>
                <instructor>Matt Linder</instructor>
                <building>SE12</building>
                <room>308</room>
                <starttime>8:30</starttime>
                <endtime>10:30</endtime>
            </class>
        </timeslot>
    </periods>
</timetable>
